LedgerCompliance/__init__.py
LedgerCompliance/client.py
LedgerCompliance/constants.py
LedgerCompliance/generic_client_interceptor.py
LedgerCompliance/header_manipulator_client_interceptor.py
LedgerCompliance/proofs.py
LedgerCompliance/stateservice.py
LedgerCompliance/types.py
LedgerCompliance/utils.py
LedgerCompliance/schema/__init__.py
LedgerCompliance/schema/lc_pb2.py
LedgerCompliance/schema/lc_pb2_grpc.py
LedgerCompliance/schema/schema_pb2.py
LedgerCompliance/schema/schema_pb2_grpc.py
ledger_compliance_py-2.1.5rc3.dist-info/METADATA
ledger_compliance_py-2.1.5rc3.dist-info/WHEEL
ledger_compliance_py-2.1.5rc3.dist-info/top_level.txt
ledger_compliance_py-2.1.5rc3.dist-info/RECORD
