Metadata-Version: 2.1
Name: ledger-compliance-py
Version: 2.1.5rc3
Summary: Python SDK for codenotary Ledger Compliance
Home-page: https://github.com/vchain-us/ledger-compliance-py
Author: CodeNotary
License: UNKNOWN
Platform: UNKNOWN
Classifier: Intended Audience :: Developers
Classifier: Topic :: Software Development :: Build Tools
Classifier: License :: OSI Approved :: Apache Software License
Classifier: Operating System :: OS Independent
Classifier: Programming Language :: Python :: 3
Classifier: Programming Language :: Python :: 3.6
Classifier: Programming Language :: Python :: 3.7
Classifier: Programming Language :: Python :: 3.8
Requires-Python: >=3.6
Requires-Dist: grpcio (>=1.26.0)
Requires-Dist: dataclasses (>=0.6)
Requires-Dist: protobuf (>=3.13.0)
Requires-Dist: google-api (>=0.1.12)
Requires-Dist: google-api-core (>=1.22.0)
